{
  "groups": [{
    "name": "activemq",
    "type": "org.springframework.cloud.stream.binder.jms.activemq.config.ActiveMQConfigurationProperties",
    "sourceType": "org.springframework.cloud.stream.binder.jms.activemq.config.ActiveMQConfigurationProperties"
  }],
  "properties": [
    {
      "name": "activemq.host",
      "type": "java.lang.String",
      "description": "Host of activeMQ server e.g. 192.168.99.100",
      "sourceType": "org.springframework.cloud.stream.binder.jms.activemq.config.ActiveMQConfigurationProperties"
    },
    {
      "name": "activemq.password",
      "type": "java.lang.String",
      "description": "Password, e.g. admin",
      "sourceType": "org.springframework.cloud.stream.binder.jms.activemq.config.ActiveMQConfigurationProperties"
    },
    {
      "name": "activemq.username",
      "type": "java.lang.String",
      "description": "Username, e.g. admin",
      "sourceType": "org.springframework.cloud.stream.binder.jms.activemq.config.ActiveMQConfigurationProperties"
    }
  ],
  "hints": []
}
